spacedinvaders/__init__.py
spacedinvaders/constants.py
spacedinvaders/exceptions.py
spacedinvaders/letters.py
spacedinvaders/sounds.py
spacedinvaders/units.py
spacedinvaders/utils.py
spacedinvaders/media/coin.wav
spacedinvaders/media/explosion.wav
spacedinvaders/media/hadouken.wav
spacedinvaders/media/invader.wav
spacedinvaders/media/killshot.wav
spacedinvaders/media/mystery.wav
spacedinvaders/media/shoot.wav
spacedinvaders-0.0.5.dist-info/LICENSE
spacedinvaders-0.0.5.dist-info/METADATA
spacedinvaders-0.0.5.dist-info/WHEEL
spacedinvaders-0.0.5.dist-info/entry_points.txt
spacedinvaders-0.0.5.dist-info/top_level.txt
spacedinvaders-0.0.5.dist-info/RECORD
