Metadata-Version: 2.1
Name: spacedinvaders
Version: 0.0.5
Summary: A textual, terminal spin on an arcade classic
Home-page: https://github.com/yawpitch/spacedinvaders
Author: Michael Morehouse
Author-email: yawpitch@yawpitchroll.com
License: UNKNOWN
Keywords: space invaders classic arcade game
Platform: UNKNOWN
Classifier: Programming Language :: Python :: 3
Classifier: Programming Language :: Python :: 3 :: Only
Classifier: Programming Language :: Python :: 3.7
Classifier: Programming Language :: Python :: 3.8
Classifier: Programming Language :: Python :: 3.9
Classifier: Programming Language :: Python :: 3.10
Classifier: Programming Language :: Python :: Implementation :: CPython
Classifier: License :: OSI Approved :: GNU General Public License v3 or later (GPLv3+)
Classifier: Operating System :: POSIX
Classifier: Operating System :: POSIX :: Linux
Classifier: Environment :: Console :: Curses
Classifier: Intended Audience :: Education
Classifier: Intended Audience :: End Users/Desktop
Classifier: Topic :: Games/Entertainment
Classifier: Topic :: Games/Entertainment :: Arcade
Classifier: Typing :: Typed
Requires-Python: >=3.7
Provides-Extra: sounds
Requires-Dist: simpleaudio ; extra == 'sounds'
